{
  "sortedMiddleware": [
    "/"
  ],
  "middleware": {
    "/": {
      "env": [
        "NEXT_PUBLIC_SUPABASE_URL",
        "NEXT_PUBLIC_SUPABASE_ANON_KEY"
      ],
      "files": [
        "server/edge-runtime-webpack.js",
        "server/middleware.js"
      ],
      "name": "middleware",
      "page": "/",
      "matchers": [
        {
          "regexp": "^/.*$",
          "originalSource": "/:path*"
        }
      ],
      "wasm": [],
      "assets": []
    }
  },
  "functions": {},
  "version": 2
}